yank/__init__.py
yank/browser.py
yank/constants.py
yank/exceptions.py
yank/history.py
yank/interface.py
yank/interface_database_mixin.py
yank/interface_display_mixin.py
yank/request.py
yank/response.py
yank/target.py
yank/tools/__init__.py
yank/tools/display.py
yank/yanker.py
yank/yanker_display_mixin.py
yank/yanker_util_mixin.py
yank-1.0.0.dist-info/LICENSE
yank-1.0.0.dist-info/WHEEL
yank-1.0.0.dist-info/METADATA
yank-1.0.0.dist-info/RECORD
